rotation_forest/__init__.py
rotation_forest/_exceptions.py
rotation_forest/rotation_forest.py
rotation_forest/tests/__init__.py
rotation_forest/tests/test_rotation_forest.py
rotation_forest-0.4.dist-info/LICENSE
rotation_forest-0.4.dist-info/METADATA
rotation_forest-0.4.dist-info/WHEEL
rotation_forest-0.4.dist-info/top_level.txt
rotation_forest-0.4.dist-info/RECORD
